{
  "nodes": [
    {
      "id": 0,
      "demand": 0,
      "priority": 0,
      "x": 50.0,
      "y": 50.0
    },
    {
      "id": 1,
      "demand": 4,
      "priority": 4,
      "x": 62.55,
      "y": 7.25
    },
    {
      "id": 2,
      "demand": 1,
      "priority": 2,
      "x": 25.09,
      "y": 71.28
    },
    {
      "id": 3,
      "demand": 4,
      "priority": 5,
      "x": 58.14,
      "y": 7.86
    },
    {
      "id": 4,
      "demand": 2,
      "priority": 3,
      "x": 25.94,
      "y": 59.18
    },
    {
      "id": 5,
      "demand": 2,
      "priority": 3,
      "x": 69.44,
      "y": 68.12
    },
    {
      "id": 6,
      "demand": 3,
      "priority": 5,
      "x": 28.62,
      "y": 68.46
    },
    {
      "id": 7,
      "demand": 4,
      "priority": 4,
      "x": 67.83,
      "y": 35.62
    },
    {
      "id": 8,
      "demand": 7,
      "priority": 5,
      "x": 91.15,
      "y": 35.29
    },
    {
      "id": 9,
      "demand": 1,
      "priority": 4,
      "x": 20.86,
      "y": 66.6
    },
    {
      "id": 10,
      "demand": 1,
      "priority": 3,
      "x": 70.68,
      "y": 53.26
    },
    {
      "id": 11,
      "demand": 3,
      "priority": 2,
      "x": 54.68,
      "y": 79.65
    },
    {
      "id": 12,
      "demand": 2,
      "priority": 2,
      "x": 61.45,
      "y": 40.35
    },
    {
      "id": 13,
      "demand": 1,
      "priority": 1,
      "x": 74.58,
      "y": 93.67
    },
    {
      "id": 14,
      "demand": 6,
      "priority": 3,
      "x": 82.98,
      "y": 39.21
    },
    {
      "id": 15,
      "demand": 5,
      "priority": 4,
      "x": 78.92,
      "y": 35.32
    },
    {
      "id": 16,
      "demand": 3,
      "priority": 5,
      "x": 68.16,
      "y": 66.52
    },
    {
      "id": 17,
      "demand": 4,
      "priority": 3,
      "x": 53.07,
      "y": 27.03
    },
    {
      "id": 18,
      "demand": 2,
      "priority": 3,
      "x": 35.55,
      "y": 70.8
    },
    {
      "id": 19,
      "demand": 1,
      "priority": 1,
      "x": 66.62,
      "y": 80.86
    },
    {
      "id": 20,
      "demand": 4,
      "priority": 3,
      "x": 25.61,
      "y": 7.89
    }
  ],
  "edges": [
    {
      "u": 0,
      "v": 12,
      "cost": 14.97,
      "reliability": 0.97
    },
    {
      "u": 0,
      "v": 10,
      "cost": 20.94,
      "reliability": 0.92
    },
    {
      "u": 0,
      "v": 7,
      "cost": 22.91,
      "reliability": 0.85
    },
    {
      "u": 0,
      "v": 1,
      "cost": 44.55,
      "reliability": 0.93
    },
    {
      "u": 1,
      "v": 3,
      "cost": 4.45,
      "reliability": 0.78
    },
    {
      "u": 1,
      "v": 17,
      "cost": 21.93,
      "reliability": 0.87
    },
    {
      "u": 1,
      "v": 7,
      "cost": 28.86,
      "reliability": 0.88
    },
    {
      "u": 0,
      "v": 2,
      "cost": 32.76,
      "reliability": 0.83
    },
    {
      "u": 2,
      "v": 9,
      "cost": 6.31,
      "reliability": 0.85
    },
    {
      "u": 0,
      "v": 3,
      "cost": 42.92,
      "reliability": 0.9
    },
    {
      "u": 3,
      "v": 17,
      "cost": 19.83,
      "reliability": 0.88
    },
    {
      "u": 0,
      "v": 4,
      "cost": 25.75,
      "reliability": 0.83
    },
    {
      "u": 4,
      "v": 6,
      "cost": 9.66,
      "reliability": 0.99
    },
    {
      "u": 4,
      "v": 18,
      "cost": 15.08,
      "reliability": 0.92
    },
    {
      "u": 0,
      "v": 5,
      "cost": 26.58,
      "reliability": 0.89
    },
    {
      "u": 5,
      "v": 10,
      "cost": 14.91,
      "reliability": 0.79
    },
    {
      "u": 5,
      "v": 11,
      "cost": 18.73,
      "reliability": 0.7
    },
    {
      "u": 0,
      "v": 6,
      "cost": 28.25,
      "reliability": 0.89
    },
    {
      "u": 2,
      "v": 6,
      "cost": 4.52,
      "reliability": 0.85
    },
    {
      "u": 6,
      "v": 18,
      "cost": 7.31,
      "reliability": 0.97
    },
    {
      "u": 7,
      "v": 12,
      "cost": 7.94,
      "reliability": 0.75
    },
    {
      "u": 0,
      "v": 8,
      "cost": 43.7,
      "reliability": 0.93
    },
    {
      "u": 8,
      "v": 14,
      "cost": 9.06,
      "reliability": 0.85
    },
    {
      "u": 8,
      "v": 15,
      "cost": 12.23,
      "reliability": 0.81
    },
    {
      "u": 0,
      "v": 9,
      "cost": 33.54,
      "reliability": 0.95
    },
    {
      "u": 6,
      "v": 9,
      "cost": 7.98,
      "reliability": 0.72
    },
    {
      "u": 10,
      "v": 12,
      "cost": 15.87,
      "reliability": 0.78
    },
    {
      "u": 0,
      "v": 11,
      "cost": 30.02,
      "reliability": 0.83
    },
    {
      "u": 12,
      "v": 17,
      "cost": 15.74,
      "reliability": 0.74
    },
    {
      "u": 0,
      "v": 13,
      "cost": 50.11,
      "reliability": 0.87
    },
    {
      "u": 13,
      "v": 19,
      "cost": 15.08,
      "reliability": 0.7
    },
    {
      "u": 0,
      "v": 14,
      "cost": 34.7,
      "reliability": 0.76
    },
    {
      "u": 0,
      "v": 15,
      "cost": 32.43,
      "reliability": 0.76
    },
    {
      "u": 14,
      "v": 15,
      "cost": 5.62,
      "reliability": 0.85
    },
    {
      "u": 7,
      "v": 15,
      "cost": 11.09,
      "reliability": 0.92
    },
    {
      "u": 0,
      "v": 16,
      "cost": 24.55,
      "reliability": 0.93
    },
    {
      "u": 5,
      "v": 16,
      "cost": 2.05,
      "reliability": 0.94
    },
    {
      "u": 16,
      "v": 19,
      "cost": 14.42,
      "reliability": 0.73
    },
    {
      "u": 11,
      "v": 16,
      "cost": 18.82,
      "reliability": 0.83
    },
    {
      "u": 0,
      "v": 17,
      "cost": 23.17,
      "reliability": 0.84
    },
    {
      "u": 7,
      "v": 17,
      "cost": 17.08,
      "reliability": 0.72
    },
    {
      "u": 0,
      "v": 18,
      "cost": 25.33,
      "reliability": 0.77
    },
    {
      "u": 2,
      "v": 18,
      "cost": 10.47,
      "reliability": 0.78
    },
    {
      "u": 0,
      "v": 19,
      "cost": 35.05,
      "reliability": 0.8
    },
    {
      "u": 11,
      "v": 19,
      "cost": 12.0,
      "reliability": 0.96
    },
    {
      "u": 5,
      "v": 19,
      "cost": 13.05,
      "reliability": 0.72
    },
    {
      "u": 0,
      "v": 20,
      "cost": 48.66,
      "reliability": 0.95
    },
    {
      "u": 6,
      "v": 8,
      "cost": 56.63,
      "reliability": 0.9
    },
    {
      "u": 7,
      "v": 16,
      "cost": 24.72,
      "reliability": 0.96
    }
  ],
  "vehicles": [
    {
      "id": 1,
      "capacity": 16
    },
    {
      "id": 2,
      "capacity": 10
    },
    {
      "id": 3,
      "capacity": 16
    }
  ]
}